cliff/__init__.py
cliff/__main__.py
cliff/agents/__init__.py
cliff/agents/async_agent.py
cliff/agents/openai_agent.py
cliff/cli/__init__.py
cliff/cli/app.py
cliff/cli/config.py
cliff/cli/tools.py
cliff/cli/commands/__init__.py
cliff/core/__init__.py
cliff/core/events.py
cliff/core/market.py
cliff/core/metrics.py
cliff/core/monitor.py
cliff/infrastructure/__init__.py
cliff/infrastructure/database.py
cliff/integrations/mcp/__init__.py
cliff/integrations/mcp/openai_adapter.py
cliff/integrations/mcp/builtin/__init__.py
cliff/integrations/mcp/custom/__init__.py
cliff/integrations/mcp/custom/loader.py
cliff/integrations/mcp/external/__init__.py
cliff/integrations/mcp/external/github.py
cliff/integrations/mcp/external/smithery.py
cliff/simulation/__init__.py
cliff/simulation/controller.py
cliff/simulation/orchestrator.py
cliff/streaming/__init__.py
cliff/streaming/display.py
cliff/streaming/events.py
cliff/streaming/handler.py
cliff/streaming/logger.py
cliff/streaming/unified_display.py
wardcliff-0.1.9.dist-info/METADATA
wardcliff-0.1.9.dist-info/WHEEL
wardcliff-0.1.9.dist-info/entry_points.txt
wardcliff-0.1.9.dist-info/RECORD
