Metadata-Version: 2.4
Name: wardcliff
Version: 0.1.9
Summary: Multi-agent prediction market trading simulation
Requires-Python: >=3.10
Requires-Dist: aiosqlite>=0.19.0
Requires-Dist: httpx>=0.24.0
Requires-Dist: openai-agents>=0.0.7
Requires-Dist: pydantic>=2.0.0
Requires-Dist: python-dotenv>=1.0.0
Requires-Dist: rich>=13.0.0
Requires-Dist: sqlalchemy>=2.0.0
Requires-Dist: typer[all]>=0.9.0
Provides-Extra: build
Requires-Dist: pyinstaller>=6.0.0; extra == 'build'
Provides-Extra: dev
Requires-Dist: pytest-asyncio>=0.21.0; extra == 'dev'
Requires-Dist: pytest>=7.0.0; extra == 'dev'
